LICENSE
README.md
setup.cfg
setup.py
cloudgenix/__init__.py
cloudgenix/ca_bundle.py
cloudgenix/delete_api.py
cloudgenix/get_api.py
cloudgenix/interactive.py
cloudgenix/patch_api.py
cloudgenix/post_api.py
cloudgenix/put_api.py
cloudgenix/ws_api.py
cloudgenix.egg-info/PKG-INFO
cloudgenix.egg-info/SOURCES.txt
cloudgenix.egg-info/dependency_links.txt
cloudgenix.egg-info/requires.txt
cloudgenix.egg-info/top_level.txt