Metadata-Version: 2.1
Name: cloudgenix
Version: 6.6.1b1
Summary: Python3 SDK for the CloudGenix AppFabric
Home-page: https://github.com/CloudGenix/sdk-python
Author: CloudGenix Developer Support
Author-email: developers@cloudgenix.com
License: MIT
Classifier: Development Status :: 5 - Production/Stable
Classifier: Intended Audience :: Developers
Classifier: License :: OSI Approved :: MIT License
Classifier: Programming Language :: Python :: 3.7
Classifier: Programming Language :: Python :: 3.8
Classifier: Programming Language :: Python :: 3.9
Classifier: Programming Language :: Python :: 3.10
Classifier: Programming Language :: Python :: 3.11
Classifier: Programming Language :: Python :: 3.12
License-File: LICENSE
